mindspore_federated/.commit_id
mindspore_federated/__init__.py
mindspore_federated/_mindspore_federated.cpython-38-aarch64-linux-gnu.so
mindspore_federated/default_config.py
mindspore_federated/log.py
mindspore_federated/version.py
mindspore_federated/aggregation/__init__.py
mindspore_federated/aggregation/fedprox.py
mindspore_federated/common/__init__.py
mindspore_federated/common/_checkparam.py
mindspore_federated/common/_fl_context.py
mindspore_federated/common/_fl_restful_tool.py
mindspore_federated/common/check_type.py
mindspore_federated/common/config.py
mindspore_federated/common/data_join_utils.py
mindspore_federated/common/tensor_utils.py
mindspore_federated/common/vfl_utils.py
mindspore_federated/data_join/__init__.py
mindspore_federated/data_join/client.py
mindspore_federated/data_join/context.py
mindspore_federated/data_join/io.py
mindspore_federated/data_join/server.py
mindspore_federated/data_join/worker.py
mindspore_federated/data_join/store/__init__.py
mindspore_federated/data_join/store/base_data.py
mindspore_federated/data_join/store/data_source_mgr.py
mindspore_federated/data_join/store/mysql_data.py
mindspore_federated/data_join/store/pandas_data.py
mindspore_federated/dataset/__init__.py
mindspore_federated/lib/libfederated.so
mindspore_federated/lib/libhiredis.so.1.0.0
mindspore_federated/lib/libhiredis_ssl.so.1.0.0
mindspore_federated/lib/libmindspore_federated_glog.so.0
mindspore_federated/privacy/__init__.py
mindspore_federated/privacy/dp.py
mindspore_federated/startup/__init__.py
mindspore_federated/startup/compress_config.py
mindspore_federated/startup/feature_map.py
mindspore_federated/startup/federated_local.py
mindspore_federated/startup/server_config.py
mindspore_federated/startup/ssl_config.py
mindspore_federated/startup/vertical_federated_local.py
mindspore_federated/startup/yaml_config.py
mindspore_federated/trainer/__init__.py
mindspore_federated/trainer/_fl_manager.py
mindspore_federated/trainer/hfl_model.py
mindspore_federated-0.1.0.dist-info/METADATA
mindspore_federated-0.1.0.dist-info/WHEEL
mindspore_federated-0.1.0.dist-info/top_level.txt
mindspore_federated-0.1.0.dist-info/RECORD
