Metadata-Version: 2.1
Name: mindspore-federated
Version: 0.1.0
Summary: MindSpore is a new open source deep learning training/inference framework that could be used for mobile, edge and cloud scenarios.
Home-page: https://www.mindspore.cn
Author: The MindSpore Authors
Author-email: contact@mindspore.cn
License: Apache 2.0
Download-URL: https://gitee.com/mindspore/federated/tags
Project-URL: Sources, https://gitee.com/mindspore/federated
Project-URL: Issue Tracker, https://gitee.com/mindspore/federated/issues
Keywords: mindspore machine learning
Platform: UNKNOWN
Classifier: Development Status :: 4 - Beta
Classifier: Environment :: Console
Classifier: Intended Audience :: Science/Research
Classifier: Intended Audience :: Developers
Classifier: License :: OSI Approved :: Apache Software License
Classifier: Programming Language :: Python :: 3 :: Only
Classifier: Programming Language :: Python :: 3.7
Classifier: Programming Language :: Python :: 3.8
Classifier: Programming Language :: Python :: 3.9
Classifier: Programming Language :: C++
Classifier: Topic :: Scientific/Engineering
Classifier: Topic :: Scientific/Engineering :: Artificial Intelligence
Classifier: Topic :: Software Development
Classifier: Topic :: Software Development :: Libraries
Classifier: Topic :: Software Development :: Libraries :: Python Modules
Requires-Python: >=3.7
Requires-Dist: numpy (>=1.17.0)
Requires-Dist: protobuf (>=3.13.0)
Requires-Dist: psutil (>=5.6.1)
Requires-Dist: flatbuffers (>=2.0)
Requires-Dist: PyYaml
Requires-Dist: mmh3
Requires-Dist: pandas
Requires-Dist: joblib
Requires-Dist: pymysql (>=1.0.2)
